hive/mediawiki/__init__.py
hive/mediawiki/__version__.py
hive_mediawiki-0.0.5.dist-info/METADATA
hive_mediawiki-0.0.5.dist-info/WHEEL
hive_mediawiki-0.0.5.dist-info/top_level.txt
hive_mediawiki-0.0.5.dist-info/RECORD
