Metadata-Version: 2.2
Name: hive-mediawiki
Version: 0.0.5
Summary: MediaWiki interface for Hive
Author-email: Gary Benson <gary@gbenson.net>
Project-URL: Homepage, https://github.com/gbenson/hive/tree/main/libs/mediawiki
Project-URL: Source, https://github.com/gbenson/hive
Classifier: License :: OSI Approved :: MIT License
Requires-Dist: hive-common>=0.1.0
Requires-Dist: pymediawiki
